LICENSE
MANIFEST.in
README.md
setup.py
penatesserver/__init__.py
penatesserver/__init__.pyc
penatesserver/admin.py
penatesserver/admin.pyc
penatesserver/backends.py
penatesserver/defaults.py
penatesserver/defaults.pyc
penatesserver/filelocks.py
penatesserver/filelocks.pyc
penatesserver/forms.py
penatesserver/forms.pyc
penatesserver/iniconf.py
penatesserver/iniconf.pyc
penatesserver/kerb.py
penatesserver/kerb.pyc
penatesserver/models.py
penatesserver/models.pyc
penatesserver/renderers.py
penatesserver/renderers.pyc
penatesserver/root_urls.py
penatesserver/root_urls.pyc
penatesserver/routers.py
penatesserver/routers.pyc
penatesserver/serializers.py
penatesserver/serializers.pyc
penatesserver/signals.py
penatesserver/subnets.py
penatesserver/subnets.pyc
penatesserver/utils.py
penatesserver/utils.pyc
penatesserver/views.py
penatesserver/views.pyc
penatesserver.egg-info/PKG-INFO
penatesserver.egg-info/SOURCES.txt
penatesserver.egg-info/dependency_links.txt
penatesserver.egg-info/entry_points.txt
penatesserver.egg-info/not-zip-safe
penatesserver.egg-info/requires.txt
penatesserver.egg-info/top_level.txt
penatesserver/__pycache__/__init__.cpython-34.pyc
penatesserver/__pycache__/defaults.cpython-34.pyc
penatesserver/__pycache__/iniconf.cpython-34.pyc
penatesserver/glpi/__init__.py
penatesserver/glpi/__init__.pyc
penatesserver/glpi/forms.py
penatesserver/glpi/forms.pyc
penatesserver/glpi/models.py
penatesserver/glpi/models.pyc
penatesserver/glpi/services.py
penatesserver/glpi/services.pyc
penatesserver/glpi/views.py
penatesserver/glpi/views.pyc
penatesserver/glpi/xmlrpc.py
penatesserver/glpi/xmlrpc.pyc
penatesserver/management/__init__.py
penatesserver/management/commands/__init__.py
penatesserver/management/commands/admin_user.py
penatesserver/management/commands/certificate.py
penatesserver/management/commands/group.py
penatesserver/management/commands/host.py
penatesserver/management/commands/host_remove.py
penatesserver/management/commands/keytab.py
penatesserver/management/commands/service.py
penatesserver/management/commands/service_remove.py
penatesserver/management/commands/shinken_service.py
penatesserver/management/commands/user.py
penatesserver/migrations/0001_initial.py
