Metadata-Version: 1.0
Name: penatesserver
Version: 0.7.1
Summary: No description yet.
Home-page: https://github.com/d9pouces/Penates-Server
Author: flanker
Author-email: flanker@19pouces.net
License: CeCILL-B
Platform: UNKNOWN
